__version__.py
command.py
data/Data.py
datalyzer/Exporter.py
datalyzer/__init__.py
datalyzer/sql.py
etc/__init__.py
etc/subclass.py
etc/generate/__init__.py
etc/generate/config_data.py
etc/generate/config_help.py
handler.py
main.py
sephera/CodeLoc.py
sephera/Stats.py
sephera/WalkFile.py
sephera/__init__.py
sephera/fetch_lang_support.py
sephera/get_update.py
sephera/help.py
sephera/set_cfg.py
sephera/version.py
sephera/interactive/__init__.py
sephera/interactive/confirm.py
sephera/interactive/option.py
sephera/net/network_helper.py
utils/__init__.py
utils/stdout.py
utils/utils.py
sephera-2.3.2.dist-info/METADATA
sephera-2.3.2.dist-info/WHEEL
sephera-2.3.2.dist-info/entry_points.txt
sephera-2.3.2.dist-info/licenses/LICENSE
sephera-2.3.2.dist-info/RECORD
