Metadata-Version: 2.4
Name: Sephera
Version: 2.3.2
Summary: Count, LOC, Stat your project, easy and quickly.
Project-URL: Homepage, https://github.com/Reim-developer/Sephera
Project-URL: Documentation, https://reim-developer.github.io/Sephera/
Project-URL: Repository, https://github.com/Reim-developer/Sephera
Author-email: Reim-developer <mavis.ngoc.nguyen@gmail.com>
License:                     GNU GENERAL PUBLIC LICENSE
License-File: LICENSE
Requires-Python: >=3.10
Requires-Dist: matplotlib
Requires-Dist: pyyaml
Requires-Dist: requests
Requires-Dist: rich
Requires-Dist: tabulate
